<?xml version="1.0" encoding="utf-8" ?>
<ASXML
	xmlns="https://thedevassembly.com"
	xmlns:xsi="http://www.w3.org/2001/XMLSchema-instance"
	xsi:schemaLocation="https://thedevassembly.com ASXML.xsd">

	<Group id="root group">
		<RectTransform>
			<position x="0" y="0"/>
			<size x="1920" y="1080"/>
			<anchor x="0" y="0"/>
		</RectTransform>
		
		<layoutInteraction>ignore</layoutInteraction>
		<layoutType>center-horizontal</layoutType>
		<color>#ffffffff</color>
		
		<Group id="baby group 1">
			<RectTransform>
				<position x="960" y="540"/>
				<size x="10" y="10"/>
				<anchor x="0.5" y="0.5"/>
			</RectTransform>
			
			<layoutInteraction>ignore</layoutInteraction>
			<layoutType>inherit</layoutType>
			<color>#ffffffff</color>
			<image>textures/brick_medieval.jpg</image>
		</Group>
	</Group>
</ASXML>